README.rst
setup.py
xjson/__init__.py
xjson/xjson.py
xjson.egg-info/PKG-INFO
xjson.egg-info/SOURCES.txt
xjson.egg-info/dependency_links.txt
xjson.egg-info/top_level.txt