Metadata-Version: 1.0
Name: xjson
Version: 0.1.5
Summary: allow you parse a json file with xpath syntax
Home-page: https://github.com/hhczy/xjson
Author: zhangTian
Author-email: hhczy1003@gmail.com
License: MIT License
Keywords: json,parse,xpath,syntax
Platform: any
